{
  "orders": [
    {
      "cart": [
        {
          "title": "Spicy",
          "quantity": 1,
          "price": 6.99,
          "cost": 6.99,
          "id": 4
        }
      ],
      "deliveryDetails": {
        "name": "Buba",
        "street": "jest Bubą ",
        "buildingNumber": "1",
        "apartmentNumber": "383",
        "orderDate": "28.10.2021, 16:08:13"
      },
      "id": 1
    },
    {
      "cart": [
        {
          "title": "Capriciosa",
          "quantity": 1,
          "price": 4.99,
          "cost": 4.99,
          "id": 2
        }
      ],
      "deliveryDetails": {
        "name": "Bartek",
        "street": "Ulica",
        "buildingNumber": "1",
        "apartmentNumber": "12",
        "orderDate": "28.10.2021, 17:41:52"
      },
      "id": 2
    },
    {
      "cart": [
        {
          "title": "Capriciosa",
          "quantity": 1,
          "price": 4.99,
          "cost": 4.99,
          "id": 2
        },
        {
          "title": "Cheesy",
          "quantity": 1,
          "price": 6.49,
          "cost": 6.49,
          "id": 3
        }
      ],
      "deliveryDetails": {
        "name": "test4",
        "street": "2",
        "buildingNumber": "1",
        "apartmentNumber": "",
        "orderDate": "28.10.2021, 17:52:52"
      },
      "id": 3
    },
    {
      "cart": [
        {
          "title": "Capriciosa",
          "quantity": 1,
          "price": 4.99,
          "cost": 4.99,
          "id": 2
        }
      ],
      "totalCost": 4.99,
      "deliveryDetails": {
        "name": "ta",
        "street": "te",
        "buildingNumber": "2",
        "apartmentNumber": "",
        "orderDate": "29.10.2021, 11:27:30"
      },
      "id": 4
    },
    {
      "cart": [
        {
          "title": "Pepperoni",
          "quantity": 1,
          "price": 5.99,
          "cost": 5.99,
          "id": 1
        },
        {
          "title": "Capriciosa",
          "quantity": 1,
          "price": 4.99,
          "cost": 4.99,
          "id": 2
        },
        {
          "title": "Cheesy",
          "quantity": 2,
          "price": 6.49,
          "cost": 12.98,
          "id": 3
        },
        {
          "title": "Spicy",
          "quantity": 1,
          "price": 6.99,
          "cost": 6.99,
          "id": 4
        }
      ],
      "totalCost": 30.95,
      "deliveryDetails": {
        "name": "Bartosz",
        "street": "Ulica",
        "buildingNumber": "11",
        "apartmentNumber": "3",
        "orderDate": "29.10.2021, 11:43:19"
      },
      "id": 5
    },
    {
      "cart": [
        {
          "title": "Pepperoni",
          "quantity": 1,
          "price": 5.99,
          "cost": 5.99,
          "id": 1
        },
        {
          "title": "Capriciosa",
          "quantity": 1,
          "price": 4.99,
          "cost": 4.99,
          "id": 2
        },
        {
          "title": "Cheesy",
          "quantity": 1,
          "price": 6.49,
          "cost": 6.49,
          "id": 3
        }
      ],
      "totalCost": 17.47,
      "deliveryDetails": {
        "name": "Buba",
        "street": "Bubica",
        "buildingNumber": "1",
        "apartmentNumber": "2",
        "orderDate": "29.10.2021, 11:44:03"
      },
      "id": 6
    },
    {
      "cart": [
        {
          "title": "Spicy",
          "quantity": 1,
          "price": 6.99,
          "cost": 6.99,
          "id": 4
        }
      ],
      "totalCost": 6.99,
      "deliveryDetails": {
        "name": "",
        "street": "",
        "buildingNumber": "",
        "apartmentNumber": "",
        "orderDate": "29.10.2021, 11:50:59"
      },
      "id": 7
    }
  ],
  "products": [
    {
      "title": "Pepperoni",
      "description": "Tasty and spicy",
      "ingredients": [
        "pepperoni sausage",
        "mozarella",
        "tomato sauce"
      ],
      "photoName": "pepperoni.png",
      "price": 5.99,
      "id": 1
    },
    {
      "title": "Capriciosa",
      "description": "With mushrooms",
      "ingredients": [
        "ham",
        "mozarella",
        "mushrooms",
        "tomato sauce"
      ],
      "photoName": "capriciosa.png",
      "price": 4.99,
      "id": 2
    },
    {
      "title": "Cheesy",
      "description": "3 types of cheese",
      "ingredients": [
        "mozarella",
        "ementaler",
        "cheddar"
      ],
      "photoName": "cheesy.png",
      "price": 6.49,
      "id": 3
    },
    {
      "title": "Spicy",
      "description": "Spicy with fire",
      "ingredients": [
        "pepperoni sausage",
        "jalapeno pepper",
        "tomato sauce"
      ],
      "photoName": "spicy.png",
      "price": 6.99,
      "id": 4
    }
  ]
}